.foundryrc
.gitignore
.travis.yml
CHANGELOG.rst
MANIFEST.in
README.rst
UNLICENSE
release.sh
requirements-dev.txt
requirements.txt
setup.py
test.sh
restructuredtext_lint/VERSION
restructuredtext_lint/__init__.py
restructuredtext_lint/__init__.pyc
restructuredtext_lint/cli.py
restructuredtext_lint/cli.pyc
restructuredtext_lint/lint.py
restructuredtext_lint/lint.pyc
restructuredtext_lint.egg-info/PKG-INFO
restructuredtext_lint.egg-info/SOURCES.txt
restructuredtext_lint.egg-info/dependency_links.txt
restructuredtext_lint.egg-info/entry_points.txt
restructuredtext_lint.egg-info/not-zip-safe
restructuredtext_lint.egg-info/requires.txt
restructuredtext_lint.egg-info/top_level.txt
restructuredtext_lint/test/__init__.py
restructuredtext_lint/test/__init__.pyc
restructuredtext_lint/test/test.py
restructuredtext_lint/test/test.pyc
restructuredtext_lint/test/test_files/invalid.rst
restructuredtext_lint/test/test_files/invalid_line_mismatch.rst
restructuredtext_lint/test/test_files/invalid_link.rst
restructuredtext_lint/test/test_files/invalid_target.rst
restructuredtext_lint/test/test_files/second_short_heading.rst
restructuredtext_lint/test/test_files/utf8.rst
restructuredtext_lint/test/test_files/valid.rst
restructuredtext_lint/test/test_files/dir/valid.rst
restructuredtext_lint/test/test_files/dir/subdir/invalid.rst