Metadata-Version: 1.1
Name: restructuredtext-lint
Version: 1.2.2
Summary: reStructuredText linter
Home-page: https://github.com/twolfson/restructuredtext-lint
Author: Todd Wolfson
Author-email: todd@twolfson.com
License: UNLICENSE
Download-URL: https://github.com/twolfson/restructuredtext-lint/archive/master.zip
Keywords: restructuredtext,restructured text,rest,rst,lint
Platform: UNKNOWN
Classifier: Development Status :: 3 - Alpha
Classifier: Intended Audience :: Developers
Classifier: License :: Public Domain
Classifier: Operating System :: OS Independent
Classifier: Topic :: Text Processing :: Markup
